{
  "environment": "web",
  "format": "html",
  "prefix": "https://storage.googleapis.com",
  "mainga": "UA-49880327-14",
  "updated": "2022-02-08T12:52:15+01:00",
  "id": "Trabajo6-MSM",
  "duration": 4,
  "title": "Trabajo6",
  "summary": "CReacion de un informe mediante wizard",
  "source": "codelab.md",
  "theme": "",
  "status": [
    "published"
  ],
  "category": [
    "codelab",
    "markdown"
  ],
  "tags": [
    "web"
  ],
  "feedback": "Un enlace en el que los usuarios puedan darte feedback (quizás creando un issue en un repositorio de git)",
  "url": "Trabajo6-MSM"
}
